odoo/addons/project_template_origin/README.rst
odoo/addons/project_template_origin/__init__.py
odoo/addons/project_template_origin/__manifest__.py
odoo/addons/project_template_origin/models/__init__.py
odoo/addons/project_template_origin/models/project.py
odoo/addons/project_template_origin/tests/__init__.py
odoo/addons/project_template_origin/tests/test_project_template_origin.py
odoo/addons/project_template_origin/views/__init__.py
odoo/addons/project_template_origin/views/project.xml
odoo_addon_project_template_origin-16.0.1.0.0.dist-info/METADATA
odoo_addon_project_template_origin-16.0.1.0.0.dist-info/WHEEL
odoo_addon_project_template_origin-16.0.1.0.0.dist-info/top_level.txt
odoo_addon_project_template_origin-16.0.1.0.0.dist-info/RECORD
