Metadata-Version: 2.1
Name: odoo-addon-project-template-origin
Version: 16.0.1.0.0
Summary: Track project template origin in project copies
Home-page: https://github.com/OCA/project
Author: Som IT Cooperatiu SCCL
License: AGPL-3
Classifier: Programming Language :: Python
Classifier: Framework :: Odoo
Classifier: Framework :: Odoo :: 16.0
Classifier: License :: OSI Approved :: GNU Affero General Public License v3
Classifier: Development Status :: 4 - Beta
Requires-Python: >=3.10
Requires-Dist: odoo-addon-project-template<16.1dev,>=16.0dev
Requires-Dist: odoo<16.1dev,>=16.0a
